README.md
setup.py
src/opex/_BBox.py
src/opex/_ObjectPrediction.py
src/opex/_ObjectPredictions.py
src/opex/_Polygon.py
src/opex/__init__.py
src/opex/_check_array_pair_polygon.py
src/opex.egg-info/PKG-INFO
src/opex.egg-info/SOURCES.txt
src/opex.egg-info/dependency_links.txt
src/opex.egg-info/requires.txt
src/opex.egg-info/top_level.txt