Metadata-Version: 1.1
Name: opex
Version: 0.0.1
Summary: Exchange format for predictions from object detection algorithms (JSON).
Home-page: UNKNOWN
Author: Corey Sterling
Author-email: corey.sterling@waikato.ac.nz
License: MIT License
Platform: UNKNOWN
Classifier: Development Status :: 4 - Beta
Classifier: License :: OSI Approved :: MIT License
Classifier: Topic :: Scientific/Engineering
Classifier: Programming Language :: Python :: 3
